fedramp_20x_mcp/__init__.py
fedramp_20x_mcp/__main__.py
fedramp_20x_mcp/cve_fetcher.py
fedramp_20x_mcp/data_loader.py
fedramp_20x_mcp/server.py
fedramp_20x_mcp/analyzers/__init__.py
fedramp_20x_mcp/analyzers/ast_utils.py
fedramp_20x_mcp/analyzers/base.py
fedramp_20x_mcp/analyzers/detection_patterns.py
fedramp_20x_mcp/analyzers/generic_adapter.py
fedramp_20x_mcp/analyzers/generic_analyzer.py
fedramp_20x_mcp/analyzers/interprocedural.py
fedramp_20x_mcp/analyzers/pattern_compiler.py
fedramp_20x_mcp/analyzers/pattern_engine.py
fedramp_20x_mcp/analyzers/pattern_tool_adapter.py
fedramp_20x_mcp/analyzers/semantic_analysis.py
fedramp_20x_mcp/analyzers/symbol_resolution.py
fedramp_20x_mcp/analyzers/frr/__init__.py
fedramp_20x_mcp/analyzers/frr/base.py
fedramp_20x_mcp/analyzers/frr/detection_patterns.py
fedramp_20x_mcp/analyzers/frr/evidence_automation.py
fedramp_20x_mcp/analyzers/frr/factory.py
fedramp_20x_mcp/analyzers/ksi/__init__.py
fedramp_20x_mcp/analyzers/ksi/base.py
fedramp_20x_mcp/analyzers/ksi/factory.py
fedramp_20x_mcp/prompts/__init__.py
fedramp_20x_mcp/prompts/api_design_guide.txt
fedramp_20x_mcp/prompts/ato_package_checklist.txt
fedramp_20x_mcp/prompts/audit_preparation.txt
fedramp_20x_mcp/prompts/authorization_boundary_review.txt
fedramp_20x_mcp/prompts/azure_ksi_automation.txt
fedramp_20x_mcp/prompts/continuous_monitoring_setup.txt
fedramp_20x_mcp/prompts/documentation_generator.txt
fedramp_20x_mcp/prompts/frr_code_review.txt
fedramp_20x_mcp/prompts/frr_family_assessment.txt
fedramp_20x_mcp/prompts/frr_implementation_roadmap.txt
fedramp_20x_mcp/prompts/gap_analysis.txt
fedramp_20x_mcp/prompts/initial_assessment_roadmap.txt
fedramp_20x_mcp/prompts/ksi_implementation_priorities.txt
fedramp_20x_mcp/prompts/migration_from_rev5.txt
fedramp_20x_mcp/prompts/quarterly_review_checklist.txt
fedramp_20x_mcp/prompts/significant_change_assessment.txt
fedramp_20x_mcp/prompts/vendor_evaluation.txt
fedramp_20x_mcp/prompts/vulnerability_remediation_timeline.txt
fedramp_20x_mcp-1.0.0.dist-info/METADATA
fedramp_20x_mcp-1.0.0.dist-info/WHEEL
fedramp_20x_mcp-1.0.0.dist-info/entry_points.txt
fedramp_20x_mcp-1.0.0.dist-info/licenses/LICENSE
fedramp_20x_mcp-1.0.0.dist-info/RECORD
