Metadata-Version: 2.4
Name: fedramp-20x-mcp
Version: 1.0.0
Summary: MCP server for querying FedRAMP 20x requirements
Project-URL: Homepage, https://github.com/KevinRabun/FedRAMP20xMCP
Project-URL: Documentation, https://github.com/KevinRabun/FedRAMP20xMCP#readme
Project-URL: Repository, https://github.com/KevinRabun/FedRAMP20xMCP
Project-URL: Issues, https://github.com/KevinRabun/FedRAMP20xMCP/issues
Author: FedRAMP 20x MCP Server Contributors
License: MIT
License-File: LICENSE
Keywords: azure,compliance,fedramp,mcp,security
Classifier: Development Status :: 5 - Production/Stable
Classifier: Intended Audience :: Developers
Classifier: License :: OSI Approved :: MIT License
Classifier: Programming Language :: Python :: 3
Classifier: Programming Language :: Python :: 3.10
Classifier: Programming Language :: Python :: 3.11
Classifier: Programming Language :: Python :: 3.12
Classifier: Topic :: Security
Classifier: Topic :: System :: Systems Administration
Requires-Python: >=3.10
Requires-Dist: httpx>=0.27.0
Requires-Dist: mcp>=1.2.0
Requires-Dist: openpyxl>=3.1.0
Requires-Dist: python-docx>=1.1.0
Requires-Dist: pyyaml>=6.0
Requires-Dist: tree-sitter-c-sharp>=0.21.0
Requires-Dist: tree-sitter-java>=0.21.0
Requires-Dist: tree-sitter-javascript>=0.21.0
Requires-Dist: tree-sitter-python>=0.21.0
Requires-Dist: tree-sitter>=0.21.0
Provides-Extra: dev
Requires-Dist: bandit>=1.7.0; extra == 'dev'
Requires-Dist: pytest-asyncio>=0.23.0; extra == 'dev'
Requires-Dist: pytest-cov>=4.1.0; extra == 'dev'
Requires-Dist: pytest>=8.0.0; extra == 'dev'
Requires-Dist: safety>=3.0.0; extra == 'dev'
